mongodb_pypi/__init__.py
mongodb_pypi/mongo_crud.py
mongodb_pypi-0.0.5.dist-info/LICENSE
mongodb_pypi-0.0.5.dist-info/METADATA
mongodb_pypi-0.0.5.dist-info/WHEEL
mongodb_pypi-0.0.5.dist-info/top_level.txt
mongodb_pypi-0.0.5.dist-info/RECORD
